server/__init__.py
server/server.py
server/common/__init__.py
server/common/decos.py
server/common/descriptors.py
server/common/errors.py
server/common/metaclasses.py
server/common/utils.py
server/common/variables.py
server/logs/__init__.py
server/logs/config_server_log.py
server/server/__init__.py
server/server/core.py
server/server/database.py
server/server/gui.py
oleup_msg_server-0.0.1.dist-info/METADATA
oleup_msg_server-0.0.1.dist-info/WHEEL
oleup_msg_server-0.0.1.dist-info/top_level.txt
oleup_msg_server-0.0.1.dist-info/RECORD
